intervalset2.py
intervalset2-1.0.2.dist-info/LICENSE
intervalset2-1.0.2.dist-info/METADATA
intervalset2-1.0.2.dist-info/WHEEL
intervalset2-1.0.2.dist-info/top_level.txt
intervalset2-1.0.2.dist-info/RECORD
