Metadata-Version: 2.2
Name: intervalset2
Version: 1.0.2
Summary: Powerful Interval Set operations.
Author-email: V Stone <vstone@126.com>
Project-URL: Homepage, https://gitee.com/stone10000/stoneutils/
Project-URL: Issue Tracker, https://gitee.com/stone10000/stoneutils/issues
Classifier: Programming Language :: Python :: 3
Classifier: License :: OSI Approved :: MIT License
Classifier: Operating System :: OS Independent
Requires-Python: >=3.8
License-File: LICENSE
